pamiq_core/__init__.py
pamiq_core/launcher.py
pamiq_core/py.typed
pamiq_core/state_persistence.py
pamiq_core/testing.py
pamiq_core/time.py
pamiq_core/console/__init__.py
pamiq_core/console/cui.py
pamiq_core/console/keyboard.py
pamiq_core/console/system_status.py
pamiq_core/console/web_api.py
pamiq_core/data/__init__.py
pamiq_core/data/buffer.py
pamiq_core/data/container.py
pamiq_core/data/interface.py
pamiq_core/data/impls/__init__.py
pamiq_core/data/impls/random_replacement_buffer.py
pamiq_core/data/impls/sequential_buffer.py
pamiq_core/gym/__init__.py
pamiq_core/gym/agent.py
pamiq_core/gym/env.py
pamiq_core/gym/types.py
pamiq_core/interaction/__init__.py
pamiq_core/interaction/agent.py
pamiq_core/interaction/env.py
pamiq_core/interaction/event_mixin.py
pamiq_core/interaction/interactions.py
pamiq_core/interaction/interval_adjustors.py
pamiq_core/interaction/modular_env.py
pamiq_core/interaction/wrappers.py
pamiq_core/model/__init__.py
pamiq_core/model/container.py
pamiq_core/model/interface.py
pamiq_core/thread/__init__.py
pamiq_core/thread/thread_control.py
pamiq_core/thread/thread_types.py
pamiq_core/thread/threads/__init__.py
pamiq_core/thread/threads/base.py
pamiq_core/thread/threads/control.py
pamiq_core/thread/threads/inference.py
pamiq_core/thread/threads/training.py
pamiq_core/torch/__init__.py
pamiq_core/torch/agent.py
pamiq_core/torch/model.py
pamiq_core/torch/trainer.py
pamiq_core/trainer/__init__.py
pamiq_core/trainer/base.py
pamiq_core/trainer/container.py
pamiq_core/utils/__init__.py
pamiq_core/utils/reflection.py
pamiq_core/utils/schedulers.py
pamiq_core-0.6.0.dist-info/METADATA
pamiq_core-0.6.0.dist-info/WHEEL
pamiq_core-0.6.0.dist-info/entry_points.txt
pamiq_core-0.6.0.dist-info/licenses/LICENSE
pamiq_core-0.6.0.dist-info/RECORD
