Metadata-Version: 2.4
Name: pamiq-core
Version: 0.6.0
Summary: Framework for building AI agents with real-time adaptive learning capabilities.
Project-URL: Repository, https://github.com/MLShukai/pamiq-core
Project-URL: Issues, https://github.com/MLShukai/pamiq-core/issues
License: MIT License
License-File: LICENSE
Keywords: AI,AMI,Autonomous Machine Intelligence,ML,Machine Learning,P-AMI<Q>,pamiq
Classifier: Development Status :: 3 - Alpha
Classifier: Intended Audience :: Developers
Classifier: Intended Audience :: Science/Research
Classifier: License :: OSI Approved :: MIT License
Classifier: Natural Language :: English
Classifier: Natural Language :: Japanese
Classifier: Operating System :: MacOS :: MacOS X
Classifier: Operating System :: Microsoft :: Windows
Classifier: Operating System :: POSIX :: Linux
Classifier: Programming Language :: Python :: 3
Classifier: Programming Language :: Python :: 3.12
Classifier: Programming Language :: Python :: 3.13
Classifier: Programming Language :: Python :: 3.14
Requires-Python: >=3.12
Requires-Dist: httpx>=0.28.1
Requires-Dist: prompt-toolkit>=3.0.51
Requires-Dist: starlette>=0.46.1
Requires-Dist: uvicorn>=0.34.0
Provides-Extra: gym
Requires-Dist: gymnasium>=1.1.1; extra == 'gym'
Provides-Extra: kbctl
Requires-Dist: pynput>=1.8.1; extra == 'kbctl'
Provides-Extra: torch
Requires-Dist: torch>=2.0.0; extra == 'torch'
